workday_cn/__init__.py
workday_cn/workday_cn.py
workday_cn-0.0.2.dist-info/METADATA
workday_cn-0.0.2.dist-info/WHEEL
workday_cn-0.0.2.dist-info/top_level.txt
workday_cn-0.0.2.dist-info/RECORD
