Metadata-Version: 2.1
Name: workday-cn
Version: 0.0.2
Summary: workday detection
Home-page: UNKNOWN
Author: lovic
Author-email: 
License: UNKNOWN
Platform: UNKNOWN
Classifier: Programming Language :: Python :: 3
Classifier: License :: OSI Approved :: GNU Affero General Public License v3 or later (AGPLv3+)
Classifier: Operating System :: POSIX :: Linux
Requires-Python: >=3.6
